workstation/__init__.py
workstation/quickstart.py
workstation-0.0.3.data/scripts/immutableworkstation.py
workstation-0.0.3.data/scripts/update_ubuntu_host.sh
workstation-0.0.3.dist-info/DESCRIPTION.rst
workstation-0.0.3.dist-info/METADATA
workstation-0.0.3.dist-info/RECORD
workstation-0.0.3.dist-info/WHEEL
workstation-0.0.3.dist-info/metadata.json
workstation-0.0.3.dist-info/top_level.txt
