Metadata-Version: 2.0
Name: workstation
Version: 0.0.3
Summary: An approach to Immutable Workstations on various hosts
Home-page: UNKNOWN
Author: See AUTHORS.txt
Author-email: UNKNOWN
License: UNKNOWN
Platform: UNKNOWN
Requires-Dist: mikado-core
